<?xml version="1.0" encoding="utf-8" ?>
<Defs>
    <ThingDef ParentName="BaseHumanMakeableGun">
        <defName>Gun_Gha_PlasmaRifle</defName>
        <label>plasma assault rifle</label>
        <description>The plasma rifle fires superheated bolts of plasma, each shot stabilized in a containment field for accuracy and power. On impact, the plasma erupts, burning through armor and flesh with devastating effect. \n\n Favored by Syndicate operatives, it’s deadly against resilient targets, leaving behind scorched wounds and cauterized surfaces. High energy output means the rifle can overheat, requiring brief cooldowns during sustained fire.</description>
        <techLevel>Spacer</techLevel>
        <graphicData>
          <texPath>Things/Item/Equipment/WeaponRanged/Gha_PlasmaRifle</texPath>
          <graphicClass>Graphic_Single</graphicClass>
          <drawSize>1.2</drawSize>
        </graphicData>
        <soundInteract>Interact_ChargeRifle</soundInteract>
        <statBases>
          <WorkToMake>45000</WorkToMake>
          <Mass>4.6</Mass>
          <AccuracyTouch>0.55</AccuracyTouch>
          <AccuracyShort>0.64</AccuracyShort>
          <AccuracyMedium>0.75</AccuracyMedium>
          <AccuracyLong>0.55</AccuracyLong>
          <RangedWeapon_Cooldown>2.00</RangedWeapon_Cooldown>
        </statBases>

        <recipeMaker>
          <researchPrerequisite>Gha_Research_Plasma_Weaponry</researchPrerequisite>
          <skillRequirements>
            <Crafting>7</Crafting>
          </skillRequirements>
          <recipeUsers Inherit="False">
            <li>FabricationBench</li>
          </recipeUsers>
          <displayPriority>200</displayPriority>
        </recipeMaker>
        <costList>
          <Plasteel>75</Plasteel>
          <ComponentSpacer>2</ComponentSpacer>
          <Shard>2</Shard>
        </costList>
        <thingSetMakerTags>
          <li>RewardStandardQualitySuper</li>
        </thingSetMakerTags>
        <weaponTags>
          <li>SpacerGun</li>
        </weaponTags>
        <tradeTags>
          <li>WeaponRanged</li>
        </tradeTags>
        <weaponClasses>
          <li>RangedLight</li>
        </weaponClasses>
        <verbs>
          <li>
            <verbClass>Verb_Shoot</verbClass>
            <hasStandardCommand>true</hasStandardCommand>
            <defaultProjectile>Bullet_Gha_PlasmaRifle</defaultProjectile>
            <warmupTime>1.3</warmupTime>
            <range>30.5</range>
            <ticksBetweenBurstShots>12</ticksBetweenBurstShots>
            <burstShotCount>5</burstShotCount>
            <soundCast>Gha_Shot_PlasmaRifle</soundCast>
            <soundCastTail>GunTail_Medium</soundCastTail>
            <muzzleFlashScale>9</muzzleFlashScale>
          </li>
        </verbs>
        <tools>
          <li>
            <label>stock</label>
            <capacities>
              <li>Blunt</li>
            </capacities>
            <power>9</power>
            <cooldownTime>2</cooldownTime>
          </li>
          <li>
            <label>barrel</label>
            <capacities>
              <li>Blunt</li>
              <li>Poke</li>
            </capacities>
            <power>9</power>
            <cooldownTime>2</cooldownTime>
          </li>
        </tools>
      </ThingDef>
      <ThingDef ParentName="BaseBullet">
        <defName>Bullet_Gha_PlasmaRifle</defName>
        <label>plasma shot</label>
        <graphicData>
          <texPath>Things/Projectiles/Det_Bullet_Plasma</texPath>
          <graphicClass>Graphic_Single</graphicClass>
        </graphicData>
        <projectile>
          <damageDef>Gha_PlasmaDamage</damageDef>
          <damageAmountBase>17</damageAmountBase>
          <armorPenetrationBase>0.65</armorPenetrationBase>
          <speed>75</speed>
        </projectile>
      </ThingDef>

<!-- Plasma Pistol -->
<ThingDef ParentName="BaseHumanMakeableGun">
  <defName>Gun_Gha_PlasmaPistol</defName>
  <label>plasma pistol</label>
  <description>The Plasma Pistol delivers a single, highly accurate shot of superheated plasma, designed for precise, controlled fire. Each shot is carefully stabilized, allowing it to burn through armor and flesh alike with deadly efficiency. Compact and reliable, this weapon is favored by Syndicate agents needing power in a sidearm, perfect for quick, lethal encounters without the risk of overheating during extended use.</description>
  <techLevel>Spacer</techLevel>
  <graphicData>
    <texPath>Things/Item/Equipment/WeaponRanged/Gha_PlasmaPistol</texPath>
    <graphicClass>Graphic_Single</graphicClass>
    <drawSize>1.0</drawSize>
  </graphicData>
  <soundInteract>Interact_ChargeRifle</soundInteract>
  <statBases>
    <WorkToMake>45000</WorkToMake>
    <Mass>4.6</Mass>
    <AccuracyTouch>0.70</AccuracyTouch>
    <AccuracyShort>0.84</AccuracyShort>
    <AccuracyMedium>0.75</AccuracyMedium>
    <AccuracyLong>0.45</AccuracyLong>
    <RangedWeapon_Cooldown>1.50</RangedWeapon_Cooldown>
  </statBases>

  <recipeMaker>
    <researchPrerequisite>Gha_Research_Plasma_Weaponry</researchPrerequisite>
    <skillRequirements>
      <Crafting>7</Crafting>
    </skillRequirements>
    <recipeUsers Inherit="False">
      <li>FabricationBench</li>
    </recipeUsers>
    <displayPriority>200</displayPriority>
  </recipeMaker>
  <costList>
    <Plasteel>50</Plasteel>
    <ComponentSpacer>2</ComponentSpacer>
    <Shard>1</Shard>
  </costList>
  <thingSetMakerTags>
    <li>RewardStandardQualitySuper</li>
  </thingSetMakerTags>
  <weaponTags>
    <li>SpacerGun</li>
  </weaponTags>
  <tradeTags>
    <li>WeaponRanged</li>
  </tradeTags>
  <weaponClasses>
    <li>RangedLight</li>
  </weaponClasses>
  <verbs>
    <li>
      <verbClass>Verb_Shoot</verbClass>
      <hasStandardCommand>true</hasStandardCommand>
      <defaultProjectile>Bullet_Gha_PlasmaPistol</defaultProjectile>
      <warmupTime>1.2</warmupTime>
      <range>25.5</range>
      <ticksBetweenBurstShots>6</ticksBetweenBurstShots>
      <burstShotCount>1</burstShotCount>
      <soundCast>Gha_Shot_PlasmaRifle</soundCast>
      <soundCastTail>GunTail_Medium</soundCastTail>
      <muzzleFlashScale>10</muzzleFlashScale>
    </li>
  </verbs>
  <tools>
    <li>
      <label>stock</label>
      <capacities>
        <li>Blunt</li>
      </capacities>
      <power>9</power>
      <cooldownTime>2</cooldownTime>
    </li>
    <li>
      <label>barrel</label>
      <capacities>
        <li>Blunt</li>
        <li>Poke</li>
      </capacities>
      <power>9</power>
      <cooldownTime>2</cooldownTime>
    </li>
  </tools>
</ThingDef>
<ThingDef ParentName="BaseBullet">
  <defName>Bullet_Gha_PlasmaPistol</defName>
  <label>plasma shot</label>
  <graphicData>
    <texPath>Things/Projectiles/Det_Bullet_Plasma</texPath>
    <graphicClass>Graphic_Single</graphicClass>
  </graphicData>
  <projectile>
    <damageDef>Gha_PlasmaDamage</damageDef>
    <damageAmountBase>65</damageAmountBase>
    <armorPenetrationBase>0.75</armorPenetrationBase>
    <speed>75</speed>
  </projectile>
</ThingDef>

<!-- Plasma Caster -->
<ThingDef ParentName="BaseHumanMakeableGun">
  <defName>Gun_Gha_PlasmaCaster</defName>
  <label>plasma caster </label>
  <description>The Plasma Caster unleashes rapid volleys of superheated plasma, each shot sacrifices precision for sheer volume, making it ideal to overwhelm single targets or swarms. However, sustained use risks overheating, requiring careful timing in prolonged engagements.</description>
  <techLevel>Spacer</techLevel>
  <graphicData>
    <texPath>Things/Item/Equipment/WeaponRanged/Gha_PlasmaCaster</texPath>
    <graphicClass>Graphic_Single</graphicClass>
    <drawSize>1.0</drawSize>
  </graphicData>
  <soundInteract>Interact_ChargeRifle</soundInteract>
  <statBases>
    <WorkToMake>45000</WorkToMake>
    <Mass>4.6</Mass>
    <AccuracyTouch>0.70</AccuracyTouch>
    <AccuracyShort>0.84</AccuracyShort>
    <AccuracyMedium>0.75</AccuracyMedium>
    <AccuracyLong>0.45</AccuracyLong>
    <RangedWeapon_Cooldown>1.50</RangedWeapon_Cooldown>
  </statBases>

  <recipeMaker>
    <researchPrerequisite>Gha_Research_Plasma_Weaponry</researchPrerequisite>
    <skillRequirements>
      <Crafting>7</Crafting>
    </skillRequirements>
    <recipeUsers Inherit="False">
      <li>FabricationBench</li>
    </recipeUsers>
    <displayPriority>200</displayPriority>
  </recipeMaker>
  <costList>
    <Plasteel>125</Plasteel>
    <ComponentSpacer>3</ComponentSpacer>
    <Shard>2</Shard>
  </costList>
  <thingSetMakerTags>
    <li>RewardStandardQualitySuper</li>
  </thingSetMakerTags>
  <weaponTags>
    <li>SpacerGun</li>
  </weaponTags>
  <tradeTags>
    <li>WeaponRanged</li>
  </tradeTags>
  <weaponClasses>
    <li>RangedHeavy</li>
  </weaponClasses>
  <verbs>
    <li>
      <verbClass>Verb_Shoot</verbClass>
      <hasStandardCommand>true</hasStandardCommand>
      <defaultProjectile>Bullet_Gha_PlasmaRifle</defaultProjectile>
      <warmupTime>2.0</warmupTime>
      <range>35.5</range>
      <ticksBetweenBurstShots>12</ticksBetweenBurstShots>
      <burstShotCount>15</burstShotCount>
      <soundCast>Gha_Shot_PlasmaRifle</soundCast>
      <soundCastTail>GunTail_Medium</soundCastTail>
      <muzzleFlashScale>10</muzzleFlashScale>
    </li>
  </verbs>
  <tools>
    <li>
      <label>stock</label>
      <capacities>
        <li>Blunt</li>
      </capacities>
      <power>9</power>
      <cooldownTime>2</cooldownTime>
    </li>
    <li>
      <label>barrel</label>
      <capacities>
        <li>Blunt</li>
        <li>Poke</li>
      </capacities>
      <power>9</power>
      <cooldownTime>2</cooldownTime>
    </li>
  </tools>
</ThingDef>
<ThingDef ParentName="BaseBullet">
  <defName>Bullet_Gha_PlasmaCaster</defName>
  <label>plasma shot</label>
  <graphicData>
    <texPath>Things/Projectiles/Det_Bullet_Plasma</texPath>
    <graphicClass>Graphic_Single</graphicClass>
  </graphicData>
  <projectile>
    <damageDef>Gha_Plasma_Nerve</damageDef>
    <damageAmountBase>7</damageAmountBase>
    <armorPenetrationBase>0.75</armorPenetrationBase>
    <speed>75</speed>
  </projectile>
</ThingDef>
<!--Mechanoid Weapons-->

<!-- Needler Gun-->
<ThingDef MayRequire="Ludeon.RimWorld.Biotech" ParentName="BaseGun">
  <defName>Gha_Gun_Needler</defName>
  <label>needler gun</label>
  <description>A mechanoid weapon based on the natural spines found on Gorehulks. Fires high-speed darts coated with incapacitating compounds. Designed for subduing cultists and escaped anomalies inside Syndicate facilities.</description>
  <techLevel>Spacer</techLevel>
  <graphicData>
    <texPath>Things/Item/Equipment/WeaponRanged/Gha_Mech_Needler</texPath>
    <graphicClass>Graphic_Single</graphicClass>
  </graphicData>
  <smeltable>false</smeltable>
  <tradeability>None</tradeability>
  <!--<destroyOnDrop>true</destroyOnDrop>-->
  <relicChance>0</relicChance>
  <statBases>
    <MarketValue>1400</MarketValue>
    <Mass>2.6</Mass>
    <AccuracyTouch>0.60</AccuracyTouch>
    <AccuracyShort>0.80</AccuracyShort>
    <AccuracyMedium>0.90</AccuracyMedium>
    <AccuracyLong>0.60</AccuracyLong>
    <RangedWeapon_Cooldown>1.5</RangedWeapon_Cooldown>
  </statBases>
  <weaponTags>
    <li>MechanoidGunHeavy</li>
  </weaponTags>
  <weaponClasses>
    <li>RangedHeavy</li>
  </weaponClasses>
  <verbs>
    <li>
      <verbClass>Verb_Shoot</verbClass>
      <hasStandardCommand>true</hasStandardCommand>
      <defaultProjectile>Bullet_NeedlerGun</defaultProjectile>
      <warmupTime>1.5</warmupTime>
      <range>20.5</range>
      <ticksBetweenBurstShots>12</ticksBetweenBurstShots>
      <burstShotCount>3</burstShotCount>
      <soundCast>Shot_NeedleGun</soundCast>
      <soundCastTail>GunTail_Heavy</soundCastTail>
      <muzzleFlashScale>9</muzzleFlashScale>
    </li>
  </verbs>
  <tools>
    <li>
      <label>barrel</label>
      <capacities>
        <li>Blunt</li>
        <li>Poke</li>
      </capacities>
      <power>9</power>
      <cooldownTime>2.6</cooldownTime>
    </li>
  </tools>
</ThingDef>

<ThingDef ParentName="BaseProjectileNeolithic">
  <defName>Bullet_NeedlerGun</defName>
  <label>needler shot</label>
  <graphicData>
    <texPath>Things/Projectile/Projectile_GorehulkSpike</texPath>
    <graphicClass>Graphic_Single</graphicClass>
    <drawSize>1.4</drawSize>
  </graphicData>
  <projectile>
    <damageDef>NeedlerStun</damageDef>
    <damageAmountBase>7</damageAmountBase>
    <armorPenetrationBase>0.35</armorPenetrationBase>
    <stoppingPower>1.5</stoppingPower>
    <speed>70</speed>
  </projectile>
</ThingDef>

<!--Plasma Gun-->
<ThingDef ParentName="BaseGun">
  <defName>Gun_Gha_VanguardPlasmaRifle</defName>
  <label>vanguard plasma spewer</label>
  <description>A plasma weapon which fires a concentrated energy beam. The narrow, superheated stream can pierce heavy armor and burn through flesh with ease.</description>
  <techLevel>Spacer</techLevel>
  <graphicData>
    <texPath>Things/Item/Equipment/WeaponRanged/Gha_Mech_Plasma</texPath>
    <graphicClass>Graphic_Single</graphicClass>
    <drawSize>1.2</drawSize>
  </graphicData>
  <smeltable>false</smeltable>
  <tradeability>None</tradeability>
  <!--<destroyOnDrop>true</destroyOnDrop>-->
  <relicChance>0</relicChance>
  <soundInteract>Interact_ChargeRifle</soundInteract>
  <statBases>
    <Mass>4.6</Mass>
    <AccuracyTouch>0.55</AccuracyTouch>
    <AccuracyShort>0.64</AccuracyShort>
    <AccuracyMedium>0.75</AccuracyMedium>
    <AccuracyLong>0.55</AccuracyLong>
    <RangedWeapon_Cooldown>2.00</RangedWeapon_Cooldown>
  </statBases>
  <weaponTags>
    <li>MechanoidGunPlasmaSpewer</li>
  </weaponTags>
  <weaponClasses>
    <li>RangedHeavy</li>
  </weaponClasses>
  <verbs>
      <li>
        <verbClass>Verb_ShootBeam</verbClass>
        <hasStandardCommand>true</hasStandardCommand>
        <warmupTime>1.0</warmupTime>
        <range>24.9</range>
        <minRange>3.9</minRange>
        <beamFullWidthRange>6.9</beamFullWidthRange>
        <burstShotCount>5</burstShotCount>
        <showBurstShotStats>false</showBurstShotStats>
        <beamWidth>6</beamWidth>
        <ticksBetweenBurstShots>22</ticksBetweenBurstShots>
        <beamDamageDef>Gha_PlasmaBeam</beamDamageDef>
        <soundCastTail>GunTail_Medium</soundCastTail>
        <muzzleFlashScale>9</muzzleFlashScale>
        <soundCastBeam>BeamGraser_Shooting</soundCastBeam>
        <beamGroundFleckDef>Fleck_BeamBurn</beamGroundFleckDef>
        <beamFleckChancePerTick>0.32</beamFleckChancePerTick>
        <beamMaxDeviation>1.5</beamMaxDeviation>
        <beamCurvature>0.6</beamCurvature>
        <beamMoteDef>Gha_Reg_Mote_GraserBeamBase</beamMoteDef>
        <beamEndEffecterDef>GraserBeam_End</beamEndEffecterDef>
        <beamChanceToStartFire>0.85</beamChanceToStartFire>
        <beamChanceToAttachFire>0.85</beamChanceToAttachFire>
        <beamFireSizeRange>0.55~0.85</beamFireSizeRange>
        <beamLineFleckDef>Fleck_BeamSpark</beamLineFleckDef>
        <beamStartOffset>0.8</beamStartOffset>
        <beamLineFleckChanceCurve>
          <points>
            <li>(0, 0)</li>
            <li>(0.65, 0.4)</li>
            <li>(1, 0.75)</li>
          </points>
        </beamLineFleckChanceCurve>
      </li>
    </verbs>
  <!--
  <verbs>
    <li>
      <verbClass>Verb_Shoot</verbClass>
      <hasStandardCommand>true</hasStandardCommand>
      <defaultProjectile>Bullet_Gha_VanguardPlasmaRifle</defaultProjectile>
      <warmupTime>1.3</warmupTime>
      <range>30.5</range>
      <ticksBetweenBurstShots>12</ticksBetweenBurstShots>
      <burstShotCount>7</burstShotCount>
      <soundCast>Gha_Shot_PlasmaRifle</soundCast>
      <soundCastTail>GunTail_Medium</soundCastTail>
      <muzzleFlashScale>9</muzzleFlashScale>
    </li>
  </verbs>
  -->
  <tools>
    <li>
      <label>stock</label>
      <capacities>
        <li>Blunt</li>
      </capacities>
      <power>9</power>
      <cooldownTime>2</cooldownTime>
    </li>
    <li>
      <label>barrel</label>
      <capacities>
        <li>Blunt</li>
        <li>Poke</li>
      </capacities>
      <power>9</power>
      <cooldownTime>2</cooldownTime>
    </li>
  </tools>
</ThingDef>

<!--Void Mechanoid Weapons-->
<!--Plasma Gun-->
<ThingDef MayRequire="Ludeon.RimWorld.Biotech" ParentName="BaseGun">
  <defName>Gun_Gha_VoidVanguardPlasmaRifle</defName>
  <label>void reaver plasma spewer</label>
  <description>A Horax-twisted plasma weapon which fires an unstable crimson beam. The chaotic energy rips through armor and flesh alike.</description>
  <techLevel>Spacer</techLevel>
  <graphicData>
    <texPath>Things/Item/Equipment/WeaponRanged/Gha_VoidMech_Plasma</texPath>
    <graphicClass>Graphic_Single</graphicClass>
    <drawSize>1.2</drawSize>
  </graphicData>
  <smeltable>false</smeltable>
  <tradeability>None</tradeability>
  <!--<destroyOnDrop>true</destroyOnDrop>-->
  <relicChance>0</relicChance>
  <soundInteract>Interact_ChargeRifle</soundInteract>
  <statBases>
    <Mass>4.6</Mass>
    <AccuracyTouch>0.55</AccuracyTouch>
    <AccuracyShort>0.64</AccuracyShort>
    <AccuracyMedium>0.75</AccuracyMedium>
    <AccuracyLong>0.55</AccuracyLong>
    <RangedWeapon_Cooldown>2.00</RangedWeapon_Cooldown>
  </statBases>
  <weaponTags>
    <li>MechanoidGunHeavy</li>
  </weaponTags>
  <weaponClasses>
    <li>RangedHeavy</li>
  </weaponClasses>
  <verbs>
      <li>
        <verbClass>Verb_ShootBeam</verbClass>
        <hasStandardCommand>true</hasStandardCommand>
        <warmupTime>1.0</warmupTime>
        <range>24.9</range>
        <minRange>3.9</minRange>
        <beamFullWidthRange>6.9</beamFullWidthRange>
        <burstShotCount>5</burstShotCount>
        <showBurstShotStats>false</showBurstShotStats>
        <beamWidth>6</beamWidth>
        <ticksBetweenBurstShots>22</ticksBetweenBurstShots>
        <beamDamageDef>Gha_PlasmaBeam_Void</beamDamageDef>
        <soundCastTail>GunTail_Medium</soundCastTail>
        <muzzleFlashScale>9</muzzleFlashScale>
        <soundCastBeam>BeamGraser_Shooting</soundCastBeam>
        <beamGroundFleckDef>Fleck_BeamBurn</beamGroundFleckDef>
        <beamFleckChancePerTick>0.32</beamFleckChancePerTick>
        <beamMaxDeviation>1.5</beamMaxDeviation>
        <beamCurvature>0.6</beamCurvature>
        <beamMoteDef>Gha_Void_Mote_GraserBeamBase</beamMoteDef>
        <beamEndEffecterDef>GraserBeam_End</beamEndEffecterDef>
        <beamChanceToStartFire>0.85</beamChanceToStartFire>
        <beamChanceToAttachFire>0.85</beamChanceToAttachFire>
        <beamFireSizeRange>0.55~0.85</beamFireSizeRange>
        <beamLineFleckDef>Fleck_BeamSpark</beamLineFleckDef>
        <beamStartOffset>0.8</beamStartOffset>
        <beamLineFleckChanceCurve>
          <points>
            <li>(0, 0)</li>
            <li>(0.65, 0.4)</li>
            <li>(1, 0.75)</li>
          </points>
        </beamLineFleckChanceCurve>
      </li>
    </verbs>
  <tools>
    <li>
      <label>stock</label>
      <capacities>
        <li>Blunt</li>
      </capacities>
      <power>9</power>
      <cooldownTime>2</cooldownTime>
    </li>
    <li>
      <label>barrel</label>
      <capacities>
        <li>Blunt</li>
        <li>Poke</li>
      </capacities>
      <power>9</power>
      <cooldownTime>2</cooldownTime>
    </li>
  </tools>
</ThingDef>

<!-- Void Needler-->
<ThingDef ParentName="BaseGun">
  <defName>Gha_Gun_VoidNeedler</defName>
  <label>spiker</label>
  <description>Once a tool of containment, now twisted by Horax rituals. This weapon fires jagged, metal darts that no longer incapacitate, but instead rip through flesh to inflict maximum pain and suffering. More brutal than its original form, it exists only to harm.</description>
  <techLevel>Spacer</techLevel>
  <graphicData>
    <texPath>Things/Item/Equipment/WeaponRanged/Gha_VoidMech_Needler</texPath>
    <graphicClass>Graphic_Single</graphicClass>
  </graphicData>
  <smeltable>false</smeltable>
  <tradeability>None</tradeability>
  <!--<destroyOnDrop>true</destroyOnDrop>-->
  <relicChance>0</relicChance>
  <statBases>
    <MarketValue>1400</MarketValue>
    <Mass>2.6</Mass>
    <AccuracyTouch>0.60</AccuracyTouch>
    <AccuracyShort>0.80</AccuracyShort>
    <AccuracyMedium>0.90</AccuracyMedium>
    <AccuracyLong>0.60</AccuracyLong>
    <RangedWeapon_Cooldown>1.5</RangedWeapon_Cooldown>
  </statBases>
  <weaponTags>
    <li>MechanoidGunHeavy</li>
  </weaponTags>
  <weaponClasses>
    <li>RangedHeavy</li>
  </weaponClasses>
  <verbs>
    <li>
      <verbClass>Verb_Shoot</verbClass>
      <hasStandardCommand>true</hasStandardCommand>
      <defaultProjectile>Bullet_VoidNeedlerGun</defaultProjectile>
      <warmupTime>1.5</warmupTime>
      <range>20.5</range>
      <ticksBetweenBurstShots>12</ticksBetweenBurstShots>
      <burstShotCount>9</burstShotCount>
      <soundCast>Gorehulk_Spine_Launch</soundCast>
      <soundCastTail>GunTail_Heavy</soundCastTail>
      <muzzleFlashScale>9</muzzleFlashScale>
    </li>
  </verbs>
  <tools>
    <li>
      <label>barrel</label>
      <capacities>
        <li>Blunt</li>
        <li>Poke</li>
      </capacities>
      <power>9</power>
      <cooldownTime>2.6</cooldownTime>
    </li>
  </tools>
</ThingDef>
<ThingDef ParentName="BaseProjectileNeolithic">
  <defName>Bullet_VoidNeedlerGun</defName>
  <label>needler shot</label>
  <graphicData>
    <texPath>Things/Projectile/Projectile_GorehulkSpike</texPath>
    <graphicClass>Graphic_Single</graphicClass>
    <drawSize>1.3</drawSize>
  </graphicData>
  <projectile>
    <damageDef>VoidStun</damageDef>
    <damageAmountBase>10</damageAmountBase>
    <armorPenetrationBase>0.35</armorPenetrationBase>
    <stoppingPower>1.5</stoppingPower>
    <speed>70</speed>
  </projectile>
</ThingDef>
</Defs>
